templaer/__init__.py
templaer/__main__.py
templaer/helper.py
templaer/main.png
templaer/mainlib.py
templaer/pypars.py
templaer/readme.md
templaer-0.1.6.2.dist-info/WHEEL
templaer-0.1.6.2.dist-info/METADATA
templaer-0.1.6.2.dist-info/RECORD
