Metadata-Version: 2.1
Name: templaer
Version: 0.1.6.2
Summary: Templaer - универсальный CLI шаблонизатор конфигурационных файлов, основанный на Jinja2
Home-page: https://github.com/denisxab/templaer
License: Apache-2.0
Keywords: template,jinja2
Author: Denis
Author-email: pro-progerkustov@yandex.ru
Requires-Python: >=3.11,<4.0
Classifier: License :: OSI Approved :: Apache Software License
Classifier: Programming Language :: Python :: 3
Classifier: Programming Language :: Python :: 3.11
Requires-Dist: jinja2 (>=3.1.2,<4.0.0)
Project-URL: Repository, https://github.com/denisxab/templaer
